igrinsdr_helper/__init__.py
igrinsdr_helper/igrinsdr_tree.py
igrinsdr_helper-0.1.0.dist-info/METADATA
igrinsdr_helper-0.1.0.dist-info/WHEEL
igrinsdr_helper-0.1.0.dist-info/RECORD
