Metadata-Version: 2.4
Name: igrinsdr-helper
Version: 0.1.0
Summary: Helper module for igrinsdr
Author: Jae-Joon Lee
Author-email: lee.j.joon@gmail.com
Requires-Python: >=3.10,<3.13
Classifier: Programming Language :: Python :: 3
Classifier: Programming Language :: Python :: 3.10
Classifier: Programming Language :: Python :: 3.11
Classifier: Programming Language :: Python :: 3.12
Requires-Dist: ipytree (>=0.2.2,<0.3.0)
